odoo/addons/product_harmonized_system/README.rst
odoo/addons/product_harmonized_system/__init__.py
odoo/addons/product_harmonized_system/__manifest__.py
odoo/addons/product_harmonized_system/demo/product_demo.xml
odoo/addons/product_harmonized_system/i18n/es.po
odoo/addons/product_harmonized_system/i18n/fr.po
odoo/addons/product_harmonized_system/i18n/product_harmonized_system.pot
odoo/addons/product_harmonized_system/migrations/14.0.2.0.0/post-migration.py
odoo/addons/product_harmonized_system/models/__init__.py
odoo/addons/product_harmonized_system/models/hs_code.py
odoo/addons/product_harmonized_system/models/product_category.py
odoo/addons/product_harmonized_system/models/product_template.py
odoo/addons/product_harmonized_system/readme/CONTRIBUTORS.rst
odoo/addons/product_harmonized_system/readme/DESCRIPTION.rst
odoo/addons/product_harmonized_system/readme/INSTALL.rst
odoo/addons/product_harmonized_system/readme/USAGE.rst
odoo/addons/product_harmonized_system/security/ir.model.access.csv
odoo/addons/product_harmonized_system/security/product_hs_security.xml
odoo/addons/product_harmonized_system/static/description/icon.png
odoo/addons/product_harmonized_system/static/description/index.html
odoo/addons/product_harmonized_system/views/hs_code.xml
odoo/addons/product_harmonized_system/views/product_category.xml
odoo/addons/product_harmonized_system/views/product_template.xml
odoo14_addon_product_harmonized_system-14.0.2.3.0.dist-info/METADATA
odoo14_addon_product_harmonized_system-14.0.2.3.0.dist-info/WHEEL
odoo14_addon_product_harmonized_system-14.0.2.3.0.dist-info/top_level.txt
odoo14_addon_product_harmonized_system-14.0.2.3.0.dist-info/RECORD
